helloworld.py
topsis_K.Likhita_101803143-0.0.1.dist-info/LICENSE.txt
topsis_K.Likhita_101803143-0.0.1.dist-info/METADATA
topsis_K.Likhita_101803143-0.0.1.dist-info/WHEEL
topsis_K.Likhita_101803143-0.0.1.dist-info/top_level.txt
topsis_K.Likhita_101803143-0.0.1.dist-info/RECORD
