Metadata-Version: 2.1
Name: topsis-K.Likhita-101803143
Version: 0.0.1
Summary: Say hello!
Home-page: https://github.com/likhita-karanam/topsis-K.Likhita-101803143
Author: K.Likhita
Author-email: karanamlikhita2000@gmail.com
License: UNKNOWN
Platform: UNKNOWN
Classifier: License :: OSI Approved :: MIT License
Classifier: Programming Language :: Python :: 3
Classifier: Programming Language :: Python :: 3.4
Classifier: Programming Language :: Python :: 3.5
Classifier: Programming Language :: Python :: 3.6
Requires-Dist: blessings (~=1.7)
Provides-Extra: dev
Requires-Dist: pytest (>=3.7) ; extra == 'dev'
